summify_release/__init__.py
summify_release/main.py
summify_release/prompts.py
summify_release-2025.12.21114801.dist-info/METADATA
summify_release-2025.12.21114801.dist-info/WHEEL
summify_release-2025.12.21114801.dist-info/top_level.txt
summify_release-2025.12.21114801.dist-info/RECORD
