Metadata-Version: 2.4
Name: summify-release
Version: 2025.12.21114801
Summary: A new package that leverages pattern-matched interactions with language models to generate structured summaries of software updates from user-provided text snippets. It focuses on extracting key featu
Author-email: summify-release <hi@eugene.plus>
License: MIT
Project-URL: Homepage, https://github.com/chigwell/summify-release
Requires-Python: >=3.9
Requires-Dist: langchain-llm7>=0.0.0
Requires-Dist: llmatch-messages>=0.0.0
Requires-Dist: langchain-core>=0.3.0
